pha/__init__.py
pha/formatters.py
pha/matchers.py
pha/spec.py
pha/tests.py
python_html_assert-0.1.2.dist-info/DESCRIPTION.rst
python_html_assert-0.1.2.dist-info/METADATA
python_html_assert-0.1.2.dist-info/RECORD
python_html_assert-0.1.2.dist-info/WHEEL
python_html_assert-0.1.2.dist-info/metadata.json
python_html_assert-0.1.2.dist-info/top_level.txt
