Metadata-Version: 2.0
Name: python-html-assert
Version: 0.1.2
Summary: partial matching of html using a tree-based specification
Home-page: https://github.com/robjohncox/python-html-assert
Author: Robert Cox
Author-email: robjohncox@gmail.com
License: MIT License
Platform: UNKNOWN
Classifier: Development Status :: 3 - Alpha
Classifier: Intended Audience :: Developers
Classifier: License :: OSI Approved :: MIT License
Classifier: Operating System :: MacOS :: MacOS X
Classifier: Operating System :: POSIX :: Linux
Classifier: Programming Language :: Python :: 2.7
Classifier: Topic :: Software Development :: Testing
Classifier: Topic :: Utilities
Requires-Dist: beautifulsoup4 (<=4.3.2)
